[
{"title": "Rogue Legacy 2 (Simplified Chinese, English, Korean, Japanese, Traditional Chinese)", "price": "Rp 349,000"},
{"title": "Inscryption (Simplified Chinese, English, Korean, Japanese, Traditional Chinese)", "price": "Rp 349,000"},
{"title": "Deus Ex: Mankind Divided (Game)", "price": "Rp 349,000"},
{"title": "Killing Floor 2 (Simplified Chinese, English, Korean, Japanese, Traditional Chinese)", "price": "Rp 349,000"},
{"title": "Lonely Mountains: Downhill (Simplified Chinese, English, Korean, Japanese)", "price": "Rp 349,000"},
{"title": "Ratchet & Clank: Rift Apart (Simplified Chinese, English, Korean, Traditional Chinese)", "price": "Rp 349,000"},
{"title": "Horizon Forbidden West™ (Simplified Chinese, English, Korean, Thai, Japanese, Traditional Chinese)", "price": "Rp 349,000"},
{"title": "Horizon Forbidden West™ (Simplified Chinese, English, Korean, Thai, Japanese, Traditional Chinese)", "price": "Rp 349,000"},
{"title": "Hundred Days - Winemaking Simulator (Simplified Chinese, English, Korean, Japanese, Traditional Chinese)", "price": "Rp 349,000"},
{"title": "Carto (Simplified Chinese, English, Korean, Japanese, Traditional Chinese)", "price": "Rp 349,000"},
{"title": "Dodgeball Academia (Simplified Chinese, English, Japanese)", "price": "Rp 349,000"},
{"title": "The Wild at Heart (Simplified Chinese, English, Korean, Japanese)", "price": "Rp 349,000"},
{"title": "Thief (Game)", "price": "Rp 349,000"},
{"title": "MX vs ATV Legends (Simplified Chinese, English, Korean, Japanese)", "price": "Rp 349,000"},
{"title": "HUMANITY (English, Japanese)", "price": "Rp 349,000"},
{"title": "Watch Dogs: Legion PS4 & PS5 (Simplified Chinese, English, Korean, Japanese, Traditional Chinese)", "price": "Rp 349,000"},
{"title": "Watch Dogs: Legion PS4 & PS5 (Simplified Chinese, English, Korean, Japanese, Traditional Chinese)", "price": "Rp 349,000"},
{"title": "UNCHARTED: Legacy of Thieves Collection (Simplified Chinese, English, Korean, Traditional Chinese)", "price": "Rp 349,000"},
{"title": "ELEX II PS4 & PS5 (Simplified Chinese, English, Japanese)", "price": "Rp 349,000"},
{"title": "Conan Exiles (Simplified Chinese, English, Korean)", "price": "Rp 349,000"},
{"title": "Kena: Bridge of Spirits PS4 & PS5 (Simplified Chinese, English, Korean, Japanese, Traditional Chinese)", "price": "Rp 349,000"},
{"title": "Dishonored 2 (English/Chinese Ver.)", "price": "Rp 349,000"},
{"title": "TOMB RAIDER DEFINITIVE EDITION full game (English/Chinese/Korean Ver.)", "price": "Rp 349,000"},
{"title": "DOOM Eternal Standard Edition (Simplified Chinese, English, Korean, Traditional Chinese)", "price": "Rp 349,000"},
{"title": "Riders Republic PS4 & PS5 (Simplified Chinese, English, Korean, Japanese, Traditional Chinese)", "price": "Rp 589,000"},
{"title": "Wolfenstein® II: The New Colossus™ (English/Chinese Ver.)", "price": "Rp 589,000"},
{"title": "Tchia (PS4 & PS5) (Simplified Chinese, English, Korean, Japanese)", "price": "Rp 589,000"},
{"title": "The Evil Within 2 (English/Chinese/Korean Ver.)", "price": "Rp 589,000"},
{"title": "Dishonored®: Death of the Outsider™ (English/Chinese Ver.)", "price": "Rp 589,000"},
{"title": "Wolfenstein: Youngblood (English/Chinese/Korean Ver.)", "price": "Rp 589,000"},
{"title": "Thymesia (Simplified Chinese, English, Korean, Japanese, Traditional Chinese)", "price": "Rp 589,000"},
{"title": "Rune Factory 4 Special (Simplified Chinese, English, Korean, Japanese, Traditional Chinese)", "price": "Rp 589,000"},
{"title": "STORY OF SEASONS: Friends of Mineral Town (Simplified Chinese, Korean, Traditional Chinese)", "price": "Rp 589,000"},
{"title": "STORY OF SEASONS: Pioneers of Olive Town (Simplified Chinese, Korean, Traditional Chinese)", "price": "Rp 589,000"},
{"title": "Soundfall (Simplified Chinese, English, Korean, Japanese, Traditional Chinese)", "price": "Rp 589,000"},
{"title": "Soundfall (Simplified Chinese, English, Korean, Japanese, Traditional Chinese)", "price": "Rp 589,000"},
{"title": "Ghostwire: Tokyo (Simplified Chinese, English, Korean, Japanese, Traditional Chinese)", "price": "Rp 589,000"},
{"title": "Tom Clancy’s Rainbow Six Extraction PS4 & PS5 (Simplified Chinese, English, Korean, Thai, Japanese, Traditional Chinese)", "price": "Rp 589,000"},
{"title": "The Evil Within (Chinese Ver.)", "price": "Rp 589,000"},
{"title": "Wolfenstein: The Old Blood (English)", "price": "Rp 589,000"},
{"title": "Bassmaster® Fishing PS4™ and PS5™ (Simplified Chinese, English, Japanese)", "price": "Rp 589,000"},
{"title": "Life is Strange: True Colors PS4 & PS5 (Simplified Chinese, English, Japanese)", "price": "Rp 589,000"},
{"title": "The Quarry for PS4™ (Simplified Chinese, English, Korean, Japanese, Traditional Chinese)", "price": "Rp 589,000"},
{"title": "The Quarry for PS5™ (Simplified Chinese, English, Korean, Japanese, Traditional Chinese)", "price": "Rp 589,000"},
{"title": "Outer Wilds (Simplified Chinese, English, Korean, Japanese)", "price": "Rp 589,000"},
{"title": "SCARLET NEXUS PS4 & PS5 (English, Japanese)", "price": "Rp 589,000"},
{"title": "Borderlands 3 PS4™ &  PS5™ (Simplified Chinese, English, Korean, Japanese, Traditional Chinese)", "price": "Rp 589,000"},
{"title": "Sackboy: A Big Adventure PS4 & PS5 (English, Korean, Traditional Chinese)", "price": "Rp 589,000"},
{"title": "Life is Strange 2 Complete Season (English)", "price": "Rp 279,000"},
{"title": "Back 4 Blood: Standard Edition PS4 & PS5 (Simplified Chinese, English, Korean, Japanese, Traditional Chinese)", "price": "Rp 279,000"},
{"title": "DRAGON BALL FighterZ (English)", "price": "Rp 279,000"},
{"title": "Devil May Cry 5 Special Edition (English, Japanese)", "price": "Rp 279,000"},
{"title": "Immortals Fenyx Rising - Digital Standard Edition PS4 & PS5 (Simplified Chinese, English, Korean, Japanese, Traditional Chinese)", "price": "Rp 279,000"},
{"title": "Untitled Goose Game (Simplified Chinese, English, Korean, Japanese)", "price": "Rp 279,000"},
{"title": "FINAL FANTASY TYPE-0 HD (Chinese/Korean Ver.)", "price": "Rp 279,000"},
{"title": "NEO: The World Ends with You (English, Japanese)", "price": "Rp 279,000"},
{"title": "Devil May Cry 5 (English, Japanese)", "price": "Rp 279,000"},
{"title": "Life is Strange Complete Season (English)", "price": "Rp 279,000"},
{"title": "LEGO® Batman™ 3: Beyond Gotham - PlayStation®Hits (English Ver.)", "price": "Rp 279,000"},
{"title": "Far Cry 5 (Simplified Chinese, English, Korean, Traditional Chinese)", "price": "Rp 279,000"},
{"title": "TEKKEN 7 (English)", "price": "Rp 279,000"},
{"title": "Far Cry Primal - Digital Standard Edition PlayStation®Hits (Simplified Chinese, English, Korean, Traditional Chinese)", "price": "Rp 279,000"},
{"title": "EARTH DEFENSE FORCE 5 (English/Chinese/Korean Ver.)", "price": "Rp 279,000"},
{"title": "Far Cry New Dawn - Digital Standard Edition (Simplified Chinese, English, Korean)", "price": "Rp 279,000"},
{"title": "Street Fighter V: Champion Edition (Game)", "price": "Rp 279,000"},
{"title": "Haven (Simplified Chinese, English, Japanese)", "price": "Rp 279,000"},
{"title": "RAGE 2 (English/Chinese/Korean Ver.)", "price": "Rp 279,000"},
{"title": "CODE VEIN (English)", "price": "Rp 279,000"},
{"title": "Journey To The Savage Planet: Employee Of The Month (Simplified Chinese, English, Korean, Traditional Chinese)", "price": "Rp 279,000"},
{"title": "Middle-earth™: Shadow of Mordor™ (English/Chinese/Korean Ver.)", "price": "Rp 279,000"},
{"title": "MEGA DIMENSION NEPTUNE VII (Japanese Ver.)", "price": "Rp 279,000"},
{"title": "Ryu Ga Gotoku 7: Hikari To Yami No Yukue (Chinese/Japanese Ver.)", "price": "Rp 279,000"},
{"title": "Ryu Ga Gotoku 6 Inochino Uta (Chinese Ver.)", "price": "Rp 351,120"},
{"title": "Tom Clancy's Rainbow Six Siege (Simplified Chinese, English, Korean, Japanese, Traditional Chinese)", "price": "Rp 351,120"},
{"title": "LittleBigPlanet™ 3 PlayStation®Hits (English/Chinese/Korean Ver.)", "price": "Rp 351,120"},
{"title": "I Am Setsuna (English Ver.)", "price": "Rp 351,120"},
{"title": "JETT: The Far Shore + Given Time (English, Japanese)", "price": "Rp 351,120"},
{"title": "KINGDOM HEARTS HD -1.5+2.5 ReMIX- (English Ver.)", "price": "Rp 351,120"},
{"title": "KINGDOM HEARTS HD 2.8 FINAL CHAPTER PROLOGUE (English)", "price": "Rp 351,120"},
{"title": "KINGDOM HEARTS III (Chinese/Korean Ver.)", "price": "Rp 351,120"},
{"title": "Erica (English)", "price": "Rp 351,120"},
{"title": "DRAGON QUEST XI S: Echoes of an Elusive Age – Definitive Edition (Simplified Chinese, Korean, Traditional Chinese)", "price": "Rp 351,120"},
{"title": "Tom Clancy's The Division® 2 (English/Chinese/Korean/Japanese Ver.)", "price": "Rp 351,120"},
{"title": "Assassin's Creed Odyssey - Digital Standard Edition (Simplified Chinese, English, Korean, Traditional Chinese)", "price": "Rp 351,120"},
{"title": "DRAGON QUEST BUILDERS 2 (Chinese/Korean Ver.)", "price": "Rp 351,120"},
{"title": "DRAGONQUEST HEROES II Futago no Ou to Yogen no Owari (Chinese/Korean Ver.)", "price": "Rp 351,120"},
{"title": "The Elder Scrolls V: Skyrim Special Edition - PS5 & PS4 (Simplified Chinese, English, Traditional Chinese)", "price": "Rp 351,120"},
{"title": "JUDGE EYES: wills of death New Price Edition (Chinese Ver.)", "price": "Rp 351,120"},
{"title": "Adventure Time Pirates of the Enchiridion (English)", "price": "Rp 351,120"},
{"title": "Spiritfarer®: Farewell Edition (Simplified Chinese, English, Korean, Japanese, Traditional Chinese)", "price": "Rp 351,120"},
{"title": "Stray (Simplified Chinese, English, Korean, Japanese, Traditional Chinese)", "price": "Rp 351,120"},
{"title": "The Dark Pictures Anthology: Little Hope PS4 & PS5 (Simplified Chinese, English, Korean, Traditional Chinese)", "price": "Rp 351,120"},
{"title": "The Dark Pictures Anthology: Little Hope PS4 & PS5 (Simplified Chinese, English, Korean, Traditional Chinese)", "price": "Rp 351,120"},
{"title": "ODDWORLD: NEW 'N' TASTY full game (English Ver.)", "price": "Rp 351,120"},
{"title": "What Remains of Edith Finch (Simplified Chinese, English, Korean, Japanese)", "price": "Rp 351,120"},
{"title": "Mortal Shell (Simplified Chinese, English, Korean, Japanese)", "price": "Rp 351,120"},
{"title": "Yakuza: Like a Dragon PS4 & PS5 (Simplified Chinese, English, Korean, Japanese, Traditional Chinese)", "price": "Rp 271,660"},
{"title": "The Pedestrian (English)", "price": "Rp 271,660"},
{"title": "INSIDE (English/Chinese/Korean Ver.)", "price": "Rp 271,660"},
{"title": "Ryu Ga Gotoku KIWAMI (Chinese Ver.)", "price": "Rp 271,660"},
{"title": "Ryu Ga Gotoku KIWAMI2 (Chinese Ver.)", "price": "Rp 271,660"},
{"title": "The Medium (Simplified Chinese, English)", "price": "Rp 271,660"},
{"title": "DRAGON QUEST BUILDERS：Alefgard wo Fukkatsu Seyo (PS4™) (Chinese Ver.)", "price": "Rp 271,660"},
{"title": "Dragon Quest Heroes™: Yamiryuu to Sekaiju no Shiro (Chinese/Korean Ver.)", "price": "Rp 271,660"},
{"title": "DRAGON BALL XENOVERSE 2 (English)", "price": "Rp 271,660"},
{"title": "FINAL FANTASY VII REMAKE INTERGRADE (Chinese/Korean Version) (Simplified Chinese, Korean, Traditional Chinese)", "price": "Rp 271,660"},
{"title": "Ghost of Tsushima DIRECTOR’S CUT (PlayStation Plus) (Simplified Chinese, English, Korean, Thai, Japanese, Traditional Chinese)", "price": "Rp 271,660"},
{"title": "Dead by Daylight PS4™ & PS5™ (Simplified Chinese, English, Korean, Japanese, Traditional Chinese)", "price": "Rp 271,660"},
{"title": "Chorus (Simplified Chinese, English, Korean, Japanese, Traditional Chinese)", "price": "Rp 271,660"},
{"title": "EARTH DEFENSE FORCE: IRON RAIN (English/Chinese/Korean/Japanese Ver.)", "price": "Rp 271,660"},
{"title": "The Gardens Between (English, Korean, Japanese, Traditional Chinese)", "price": "Rp 271,660"},
{"title": "Ghost Recon Breakpoint - Standard Edition (English/Chinese/Korean/Japanese Ver.)", "price": "Rp 271,660"},
{"title": "OMNO (Simplified Chinese, English, Korean, Japanese, Traditional Chinese)", "price": "Rp 271,660"},
{"title": "Ghost Recon Wildlands - Digital Standard Edition (Simplified Chinese, English, Korean)", "price": "Rp 271,660"},
{"title": "Bugsnax (Simplified Chinese, English, Korean, Japanese)", "price": "Rp 271,660"},
{"title": "My Time at Portia (Simplified Chinese, English, Japanese, Traditional Chinese)", "price": "Rp 271,660"},
{"title": "Returnal™ (Simplified Chinese, English, Korean, Traditional Chinese)", "price": "Rp 271,660"},
{"title": "Demon's Souls (Simplified Chinese, English, Korean, Thai, Traditional Chinese)", "price": "Rp 271,660"},
{"title": "Assassin's Creed Chronicles - China (English, Korean, Traditional Chinese)", "price": "Rp 271,660"},
{"title": "Assassin's Creed Chronicles - India (Simplified Chinese, English, Korean, Traditional Chinese)", "price": "Rp 271,660"},
{"title": "Assassin's Creed Chronicles - Russia (Simplified Chinese, English, Korean, Traditional Chinese)", "price": "Rp 41,600"},
{"title": "Assassin's Creed® III Remastered - Digital Standard Edition (English/Chinese/Korean/Japanese Ver.)", "price": "Rp 41,600"},
{"title": "DEATHLOOP (Simplified Chinese, English, Korean, Traditional Chinese)", "price": "Rp 41,600"},
{"title": "Assassin's Creed Unity - Digital Standard Edition (English, Korean, Traditional Chinese)", "price": "Rp 41,600"},
{"title": "Hohokum™ full game (English Ver.)", "price": "Rp 41,600"},
{"title": "The Crew 2 - Digital Standard Edition (Simplified Chinese, English, Korean, Traditional Chinese)", "price": "Rp 41,600"},
{"title": "Control: Ultimate Edition (Simplified Chinese, English, Korean, Japanese, Traditional Chinese)", "price": "Rp 41,600"},
{"title": "Hollow Knight (Simplified Chinese, English, Korean, Japanese)", "price": "Rp 41,600"},
{"title": "Maneater PS4 & PS5 (Simplified Chinese, English, Korean, Japanese, Traditional Chinese)", "price": "Rp 41,600"},
{"title": "Horizon Zero Dawn™: Complete Edition PlayStation®Hits (Simplified Chinese, English, Korean)", "price": "Rp 41,600"},
{"title": "UNCHARTED 4: A Thief's End™ PlayStation®Hits (Game)", "price": "Rp 41,600"},
{"title": "UNCHARTED: The Lost Legacy™ (English/Chinese/Korean Ver.)", "price": "Rp 41,600"},
{"title": "Saints Row IV: Re-Elected (English)", "price": "Rp 41,600"},
{"title": "Saints Row: Gat out of Hell (English)", "price": "Rp 41,600"},
{"title": "Assassin's Creed Rogue Remastered - Digital Standard Edition (English, Korean, Traditional Chinese)", "price": "Rp 41,600"},
{"title": "Assassin's Creed The Ezio Collection (Simplified Chinese, English, Korean, Traditional Chinese)", "price": "Rp 41,600"},
{"title": "Human: Fall Flat PS4 & PS5 (Simplified Chinese, English, Korean, Japanese, Traditional Chinese)", "price": "Rp 41,600"},
{"title": "Monopoly Plus (English)", "price": "Rp 41,600"},
{"title": "Rabbids®Invasion: The interactive TV Show full game (English)", "price": "Rp 41,600"},
{"title": "Rayman® Legends - Digital Standard Edition PlayStation®Hits (English)", "price": "Rp 41,600"},
{"title": "Scott Pilgrim vs. The World™: The Game – Complete Edition (English)", "price": "Rp 41,600"},
{"title": "The Dark Pictures Anthology: Man of Medan PS4 & PS5 (Simplified Chinese, English, Korean, Traditional Chinese)", "price": "Rp 41,600"},
{"title": "Ys VIII -Lacrimosa of DANA- Standard Edition (Chinese Ver.)", "price": "Rp 41,600"},
{"title": "FINAL FANTASY X/X-2 HD Remaster (Chinese/Korean Ver.)", "price": "Rp 41,600"},
{"title": "SOULCALIBUR VI (English)", "price": "Rp 102,000"},
{"title": "Mortal Shell: Enhanced Edition (Simplified Chinese, English, Korean, Japanese, Traditional Chinese)", "price": "Rp 102,000"},
{"title": "STEEP - Digital Standard Edition (Simplified Chinese, English, Traditional Chinese)", "price": "Rp 102,000"},
{"title": "Everybody's Golf (English, Korean, Traditional Chinese)", "price": "Rp 102,000"},
{"title": "Shadow of the Colossus™ (English/Chinese/Korean Ver.)", "price": "Rp 102,000"},
{"title": "FINAL FANTASY XII THE ZODIAC AGE (Chinese/Korean Ver.)", "price": "Rp 102,000"},
{"title": "GRAVITY RUSH 2  (Standard Edition) (English/Chinese/Korean Ver.)", "price": "Rp 102,000"},
{"title": "Darksiders Genesis (Game)", "price": "Rp 102,000"},
{"title": "Warhammer: Chaosbane Slayer Edition (Simplified Chinese, English, Korean, Traditional Chinese)", "price": "Rp 102,000"},
{"title": "Bloodstained: Ritual of the Night (Simplified Chinese, English, Korean, Japanese, Traditional Chinese)", "price": "Rp 102,000"},
{"title": "WATCH_DOGS™ - Digital Standard Edition PlayStation®Hits (English)", "price": "Rp 102,000"},
{"title": "Terraria – PlayStation®4 Edition (English, Korean)", "price": "Rp 102,000"},
{"title": "Watch Dogs 2 - Digital Standard Edition PlayStation®Hits (Simplified Chinese, English, Korean)", "price": "Rp 102,000"},
{"title": "For Honor - Digital Standard Edition (Simplified Chinese, English, Korean)", "price": "Rp 102,000"},
{"title": "Far Cry 4 - Digital Standard Edition PlayStation®Hits (English, Korean)", "price": "Rp 102,000"},
{"title": "Friday the 13th the Game (English/Chinese Ver.)", "price": "Rp 102,000"},
{"title": "Blasphemous (Simplified Chinese, English, Korean, Japanese)", "price": "Rp 102,000"},
{"title": "Far Cry®3 Classic Edition - Digital Standard Edition (Simplified Chinese, English, Korean, Traditional Chinese)", "price": "Rp 102,000"},
{"title": "God of War (English, Korean, Traditional Chinese)", "price": "Rp 102,000"},
{"title": "MONOPOLY® Madness (Simplified Chinese, English, Korean, Japanese, Traditional Chinese)", "price": "Rp 102,000"},
{"title": "Desperados III (Simplified Chinese, English, Korean)", "price": "Rp 102,000"},
{"title": "My Friend Pedro (English)", "price": "Rp 102,000"},
{"title": "Bloodborne™ PlayStation®Hits (English/Chinese/Korean Ver.)", "price": "Rp 102,000"},
{"title": "Wreckfest (Game)", "price": "Rp 102,000"},
{"title": "Wreckfest PlayStation®5 Version (English)", "price": "Rp 347,400"},
{"title": "MediEvil (English)", "price": "Rp 347,400"},
{"title": "Dragon Star Varnir (English Ver.)", "price": "Rp 347,400"},
{"title": "The Fisherman: Fishing Planet (Simplified Chinese, English, Traditional Chinese)", "price": "Rp 347,400"},
{"title": "Tearaway™ Unfolded (Simplified Chinese, English, Korean)", "price": "Rp 347,400"},
{"title": "FINAL FANTASY VIII Remastered (English/Japanese Ver.)", "price": "Rp 347,400"},
{"title": "Ghostrunner (Simplified Chinese, English, Korean, Japanese, Traditional Chinese)", "price": "Rp 347,400"},
{"title": "ALIENATION™ (English/Chinese/Korean Ver.)", "price": "Rp 347,400"},
{"title": "Death end re;Quest (English Ver.)", "price": "Rp 347,400"},
{"title": "Hello Neighbor (Simplified Chinese, English, Korean, Japanese, Traditional Chinese)", "price": "Rp 347,400"},
{"title": "Last Stop (Simplified Chinese, English, Korean, Japanese, Traditional Chinese)", "price": "Rp 347,400"},
{"title": "Days Gone Standard Edition (Simplified Chinese, English, Korean)", "price": "Rp 347,400"},
{"title": "ONINAKI (English/Japanese Ver.)", "price": "Rp 347,400"},
{"title": "Trials® Rising - Digital Standard Edition (English/Chinese/Japanese Ver.)", "price": "Rp 347,400"},
{"title": "For The King (English/Chinese/Korean/Japanese Ver.)", "price": "Rp 347,400"},
{"title": "Ashen (English/Chinese/Korean/Japanese Ver.)", "price": "Rp 347,400"},
{"title": "Darksiders III (Game)", "price": "Rp 347,400"},
{"title": "Secret Neighbor (Simplified Chinese, English, Korean, Thai, Japanese, Traditional Chinese)", "price": "Rp 347,400"},
{"title": "Middle-earth™: Shadow of War™ (English/Chinese/Korean Ver.)", "price": "Rp 347,400"},
{"title": "FINAL FANTASY VII (English/Japanese Ver.)", "price": "Rp 347,400"},
{"title": "FINAL FANTASY VII REMAKE (Simplified Chinese, Korean, Traditional Chinese)", "price": "Rp 347,400"},
{"title": "WORLD OF FINAL FANTASY (Chinese/Korean Ver.)", "price": "Rp 347,400"},
{"title": "Call of Cthulhu® (Simplified Chinese, English, Korean)", "price": "Rp 347,400"},
{"title": "FAR CRY 3: BLOOD DRAGON CLASSIC EDITION (Simplified Chinese, English, Korean, Traditional Chinese)", "price": "Rp 347,400"},
{"title": "Killzone™ Shadow Fall PlayStation®Hits (English/Chinese/Korean Ver.)", "price": "Rp 139,500"},
{"title": "XCOM 2 (English/Chinese/Korean Ver.)", "price": "Rp 139,500"},
{"title": "Moving Out (Simplified Chinese, English, Korean, Japanese, Traditional Chinese)", "price": "Rp 139,500"},
{"title": "Totally Reliable Delivery Service (English, Korean, Japanese)", "price": "Rp 139,500"},
{"title": "FIGHTING EX LAYER (Standard Version) (English/Japanese Ver.)", "price": "Rp 139,500"},
{"title": "Detroit: Become Human™ Standard Edition (English/Chinese/Korean Ver.)", "price": "Rp 139,500"},
{"title": "Battle Chasers: Nightwar (Simplified Chinese, English, Korean, Japanese)", "price": "Rp 139,500"},
{"title": "PAW Patrol On a Roll (English)", "price": "Rp 139,500"},
{"title": "Harvest Moon®: Light of Hope Special Edition (English Ver.)", "price": "Rp 139,500"},
{"title": "The Messenger (English/Korean/Japanese Ver.)", "price": "Rp 139,500"},
{"title": "FINAL FANTASY® IX (English Ver.)", "price": "Rp 139,500"},
{"title": "The Surge 2 (English/Chinese/Korean Ver.)", "price": "Rp 139,500"},
{"title": "Prison Architect: PlayStation®4 Edition (Game)", "price": "Rp 139,500"},
{"title": "The Artful Escape (Simplified Chinese, English, Korean, Japanese, Traditional Chinese)", "price": "Rp 139,500"},
{"title": "The LEGO® Movie Videogame full game (English Ver.)", "price": "Rp 139,500"},
{"title": "Deliver Us The Moon PS4 & PS5 (Simplified Chinese, English, Korean, Japanese)", "price": "Rp 139,500"},
{"title": "Deliver Us The Moon PS4 & PS5 (Simplified Chinese, English, Korean, Japanese)", "price": "Rp 139,500"},
{"title": "Valiant Hearts: The Great War full game (English)", "price": "Rp 139,500"},
{"title": "Overcooked! 2 (Simplified Chinese, English, Korean, Japanese)", "price": "Rp 139,500"},
{"title": "Caladrius Blaze (English, Korean)", "price": "Rp 139,500"},
{"title": "The MISSING: J.J. Macfield and the Island of Memories (English/Chinese/Korean/Japanese Ver.)", "price": "Rp 139,500"},
{"title": "Destruction AllStars (Simplified Chinese, English, Korean, Traditional Chinese)", "price": "Rp 139,500"},
{"title": "inFAMOUS Second Son™ PlayStation®Hits (English/Chinese/Korean Ver.)", "price": "Rp 139,500"},
{"title": "Until Dawn™ PlayStation®Hits (English/Chinese/Korean Ver.)", "price": "Rp 139,500"},
{"title": "South Park™: The Fractured but Whole™ - Digital Standard Edition (English)", "price": "Rp 172,250"},
{"title": "GRIP (Simplified Chinese, English, Korean)", "price": "Rp 172,250"},
{"title": "Monster Jam Steel Titans 2 (English)", "price": "Rp 172,250"},
{"title": "Monster Truck Championship (Simplified Chinese, English, Korean, Thai, Traditional Chinese)", "price": "Rp 172,250"},
{"title": "The Last Guardian (English/Chinese/Korean Ver.)", "price": "Rp 172,250"},
{"title": "Batman™: Arkham Knight PlayStation®Hits (English, Korean)", "price": "Rp 172,250"},
{"title": "Observation (English/Korean/Japanese Ver.)", "price": "Rp 172,250"},
{"title": "This is the Police (Simplified Chinese, English)", "price": "Rp 172,250"},
{"title": "Golf With Your Friends (Simplified Chinese, English, Japanese, Traditional Chinese)", "price": "Rp 172,250"},
{"title": "The Crew (English)", "price": "Rp 172,250"},
{"title": "ABZU (English)", "price": "Rp 172,250"},
{"title": "JUDGE EYES: wills of death Remastered (Simplified Chinese, English, Korean, Japanese, Traditional Chinese)", "price": "Rp 172,250"},
{"title": "ReadySet Heroes (English/Chinese/Korean Ver.)", "price": "Rp 172,250"},
{"title": "This Is the Police 2 (English, Korean, Japanese, Traditional Chinese)", "price": "Rp 172,250"},
{"title": "South Park: The Stick of Truth (English)", "price": "Rp 172,250"},
{"title": "Embr (Simplified Chinese, English, Korean, Japanese, Traditional Chinese)", "price": "Rp 172,250"},
{"title": "Starlink: Battle for Atlas - Digital Edition (English/Chinese/Korean/Japanese Ver.)", "price": "Rp 172,250"},
{"title": "Marvel's Spider-Man: Miles Morales PS4 & PS5 (Simplified Chinese, English, Korean, Traditional Chinese)", "price": "Rp 172,250"},
{"title": "Hotline Miami 2: Wrong Number (English Ver.)", "price": "Rp 172,250"},
{"title": "How to Survive 2 (English)", "price": "Rp 172,250"},
{"title": "Surviving Mars (English)", "price": "Rp 172,250"},
{"title": "MATTERFALL™ (English/Chinese/Korean Ver.)", "price": "Rp 172,250"},
{"title": "Concrete Genie Digital Deluxe Edition (English, Korean, Thai, Traditional Chinese)", "price": "Rp 172,250"},
{"title": "Warhammer 40,000: Inquisitor - Martyr (English)", "price": "Rp 172,250"},
{"title": "Space Hulk: Deathwing - Enhanced Edition (English Ver.)", "price": "Rp 107,250"},
{"title": "Lawn Mowing Simulator PS4 & PS5 (Simplified Chinese, English, Korean, Japanese, Traditional Chinese)", "price": "Rp 107,250"},
{"title": "I Am Dead (Simplified Chinese, English, Korean, Japanese, Traditional Chinese)", "price": "Rp 107,250"},
{"title": "Fade to Silence (English, Japanese, Traditional Chinese)", "price": "Rp 107,250"},
{"title": "Shadow of the Beast™ (English/Chinese/Korean Ver.)", "price": "Rp 107,250"},
{"title": "ZOMBI (English, Japanese)", "price": "Rp 107,250"},
{"title": "FORECLOSED (English, Korean, Japanese, Traditional Chinese)", "price": "Rp 107,250"},
{"title": "Brothers: A Tale of Two Sons (Simplified Chinese, English, Japanese)", "price": "Rp 107,250"},
{"title": "Vampyr (English Ver.)", "price": "Rp 107,250"},
{"title": "Stellaris: Console Edition (English, Korean, Japanese)", "price": "Rp 107,250"},
{"title": "ELEX (English)", "price": "Rp 107,250"},
{"title": "Trials Fusion (English)", "price": "Rp 107,250"},
{"title": "KINGDOM HEARTS Melody of Memory (Simplified Chinese, Korean, Traditional Chinese)", "price": "Rp 107,250"},
{"title": "RESOGUN™ full game (English)", "price": "Rp 107,250"},
{"title": "KNACK full game (English/Chinese/Korean Ver.)", "price": "Rp 107,250"},
{"title": "Transference™ - Digital Edition (English/Chinese/Korean/Japanese Ver.)", "price": "Rp 107,250"},
{"title": "Observer: System Redux (Simplified Chinese, English, Korean, Japanese)", "price": "Rp 107,250"},
{"title": "The Elder Scrolls Online - PS4 (English)", "price": "Rp 107,250"},
{"title": "Eagle Flight (Simplified Chinese, English, Korean, Japanese, Traditional Chinese)", "price": "Rp 107,250"},
{"title": "Bomber Crew (English/Japanese Ver.)", "price": "Rp 107,250"},
{"title": "Space Crew: Legendary Edition (Simplified Chinese, English, Korean, Japanese, Traditional Chinese)", "price": "Rp 107,250"},
{"title": "Trials of the Blood Dragon Game (Simplified Chinese, English)", "price": "Rp 107,250"},
{"title": "Age of Wonders: Planetfall (English, Korean)", "price": "Rp 107,250"},
{"title": "No Straight Roads (Simplified Chinese, English, Korean, Malay, Japanese, Traditional Chinese)", "price": "Rp 107,250"},
{"title": "DAMASCUS GEAR : Operation Tokyo HD Edition (Japanese Ver.)", "price": "Rp 189,000"},
{"title": "Get Even (English Ver.)", "price": "Rp 189,000"},
{"title": "ADR1FT (English)", "price": "Rp 189,000"},
{"title": "BOUND: Shattered Kingdom (English/Chinese/Korean Ver.)", "price": "Rp 189,000"},
{"title": "Hue (English Ver.)", "price": "Rp 189,000"},
{"title": "Entwined™ full game (English Ver.)", "price": "Rp 189,000"},
{"title": "11-11: Memories Retold (English, Japanese)", "price": "Rp 189,000"},
{"title": "TowerFall Ascension full game (English Ver.)", "price": "Rp 189,000"},
{"title": "The Technomancer (English Ver.)", "price": "Rp 189,000"},
{"title": "Space Junkies™ - Digital Standard Edition (English/Chinese/Korean/Japanese Ver.)", "price": "Rp 189,000"},
{"title": "Star Trek: Bridge Crew - Digital Standard (English)", "price": "Rp 189,000"},
{"title": "Risk Urban Assault (English)", "price": "Rp 189,000"},
{"title": "Werewolves Within (English)", "price": "Rp 189,000"},
{"title": "TorqueL full game (English Ver.)", "price": "Rp 189,000"},
{"title": "Tetris® Effect: Connected (Simplified Chinese, English, Korean, Thai, Japanese, Traditional Chinese)", "price": "Rp 189,000"},
{"title": "Rez Infinite (Simplified Chinese, English, Korean, Japanese)", "price": "Rp 189,000"},
{"title": "Payday 2 Crimewave Edition (English)", "price": "Rp 189,000"},
{"title": "NARUTO TO BORUTO: SHINOBI STRIKER (English)", "price": "Rp 189,000"},
{"title": "Monster Truck Championship (Simplified Chinese, English, Korean, Thai, Traditional Chinese)", "price": "Rp 189,000"},
{"title": "Maneater PS4 & PS5 (Simplified Chinese, English, Korean, Japanese, Traditional Chinese)", "price": "Rp 189,000"},
{"title": "Mahjong (English)", "price": "Rp 189,000"},
{"title": "Magicka 2: Base Edition (English, Korean, Traditional Chinese)", "price": "Rp 189,000"},
{"title": "MudRunner (English Ver.)", "price": "Rp 189,000"},
{"title": "LOST SPHEAR (Japanese Ver.)", "price": "Rp 189,000"},
{"title": "Legendary Fishing Digital Edition (English/Chinese/Korean/Japanese Ver.)", "price": "Rp 345,000"},
{"title": "Life is Strange: Before the Storm Complete Season (English Ver.)", "price": "Rp 345,000"},
{"title": "Kingdom Two Crowns (English)", "price": "Rp 345,000"},
{"title": "DYNASTY WARRIORS 8 Empires full game (Japanese Ver.)", "price": "Rp 345,000"},
{"title": "Far Cry 6 - Digital Standard Edition PS4 & PS5 (Simplified Chinese, English, Korean, Thai, Japanese, Traditional Chinese)", "price": "Rp 345,000"},
{"title": "Sakuna: Of Rice and Ruin (Simplified Chinese, English, Korean, Japanese, Traditional Chinese)", "price": "Rp 345,000"},
{"title": "Bus Simulator 21 Next Stop (Simplified Chinese, English, Korean, Japanese, Traditional Chinese)", "price": "Rp 345,000"},
{"title": "Rise of the Tomb Raider: 20 Year Celebration (Game)", "price": "Rp 345,000"},
{"title": "Shadow of the Tomb Raider (English Ver.)", "price": "Rp 345,000"},
{"title": "RESIDENT EVIL 7 biohazard (Simplified Chinese, English, Korean, Thai, Japanese, Traditional Chinese)", "price": "Rp 345,000"},
{"title": "DRAGON BALL Z: KAKAROT PS4&PS5 (English)", "price": "Rp 345,000"},
{"title": "FINAL FANTASY TYPE-0 HD (English Ver.)", "price": "Rp 345,000"},
{"title": "FINAL FANTASY TYPE-0 HD (Japanese Ver.)", "price": "Rp 345,000"},
{"title": "ACE COMBAT™ 7: SKIES UNKNOWN (English, Japanese)", "price": "Rp 345,000"},
{"title": "Street Fighter V: Champion Edition (Game)", "price": "Rp 345,000"},
{"title": "Megadimension Neptunia™ VII (English Ver.)", "price": "Rp 345,000"},
{"title": "MEGADIMENSION NEPTUNIA VII (Chinese Ver.)", "price": "Rp 345,000"},
{"title": "Yakuza 6: The Song of Life (English Ver.)", "price": "Rp 345,000"},
{"title": "Ikenie to Yuki no Setsuna (Japanese Ver.)", "price": "Rp 345,000"},
{"title": "KINGDOM HEARTS III (English Ver.)", "price": "Rp 345,000"},
{"title": "DRAGON QUEST XI S: Echoes of an Elusive Age – Definitive Edition (English)", "price": "Rp 345,000"},
{"title": "DRAGON QUEST BUILDERS 2 (English Ver.)", "price": "Rp 345,000"},
{"title": "DRAGON QUEST BUILDERS 2 (Japanese Ver.)", "price": "Rp 345,000"},
{"title": "DRAGON QUEST HEROES II™ (English Ver.)", "price": "Rp 345,000"},
{"title": "DRAGONQUEST HEROES II Futago no Ou to Yogen no Owari (Japanese Ver.)", "price": "Rp 779,000"},
{"title": "Yakuza 0 (English Ver.)", "price": "Rp 779,000"},
{"title": "Ryu Ga Gotoku 0: Chikai No Basyo (Japanese Ver.)", "price": "Rp 779,000"},
{"title": "Judgment (English Ver.)", "price": "Rp 779,000"},
{"title": "Ryu Ga Gotoku 7: Hikari To Yami No Yukue International (Simplified Chinese, English, Korean, Japanese, Traditional Chinese)", "price": "Rp 779,000"},
{"title": "YAKUZA KIWAMI (English Ver.)", "price": "Rp 779,000"},
{"title": "Yakuza Kiwami 2 (English Ver.)", "price": "Rp 779,000"},
{"title": "DRAGON QUEST BUILDERS™ (English Ver.)", "price": "Rp 779,000"},
{"title": "DRAGON QUEST BUILDERS：Alefgard wo Fukkatsu Seyo (PS4™) (Japanese Ver.)", "price": "Rp 779,000"},
{"title": "DRAGON QUEST HEROES: The World Tree's Woe and the Blight Below (English Ver.)", "price": "Rp 779,000"},
{"title": "Dragon Quest Heroes™: Yamiryuu to Sekaiju no Shiro full game (Japanese Ver.)", "price": "Rp 779,000"},
{"title": "FINAL FANTASY VII REMAKE INTERGRADE (Japanese/English Version) (English, Japanese)", "price": "Rp 779,000"},
{"title": "Marvel's Guardians of the Galaxy PS4 & PS5 (English/Japanese Version) (Simplified Chinese, English, Korean, Japanese, Traditional Chinese)", "price": "Rp 779,000"},
{"title": "Oddworld: Soulstorm Enhanced Edition (Simplified Chinese, English, Japanese, Traditional Chinese)", "price": "Rp 779,000"},
{"title": "Assassin's Creed® Syndicate - Digital Standard Edition (Simplified Chinese, English, Korean, Traditional Chinese)", "price": "Rp 779,000"},
{"title": "OUTRIDERS PS4 & PS5 (English)", "price": "Rp 779,000"},
{"title": "Control: Ultimate Edition (Simplified Chinese, English, Korean, Traditional Chinese)", "price": "Rp 779,000"},
{"title": "Assassin's Creed® IV Black Flag - Digital Standard Edition – PlayStation®Hits (English)", "price": "Rp 779,000"},
{"title": "Assassin's Creed Origins - Digital Standard Edition (Simplified Chinese, English, Korean, Traditional Chinese)", "price": "Rp 779,000"},
{"title": "Assassin's Creed® Freedom Cry Standalone full game (English/Chinese/Japanese Ver.)", "price": "Rp 779,000"},
{"title": "Assetto Corsa Competizione (English, Korean)", "price": "Rp 779,000"},
{"title": "Assetto Corsa Competizione (Simplified Chinese, English, Korean, Traditional Chinese)", "price": "Rp 779,000"},
{"title": "FINAL FANTASY X/X-2 HD Remaster (English Ver.)", "price": "Rp 779,000"},
{"title": "FINAL FANTASY X/X-2 HD Remaster (Japanese Ver.)", "price": "Rp 779,000"},
{"title": "Tennis World Tour 2 (Simplified Chinese, English, Korean, Traditional Chinese)", "price": "Rp 699,000"},
{"title": "Tennis World Tour 2 - Complete Edition (Simplified Chinese, English, Korean, Traditional Chinese)", "price": "Rp 699,000"},
{"title": "FINAL FANTASY XII THE ZODIAC AGE (English/Japanese Ver.)", "price": "Rp 699,000"},
{"title": "Warhammer Chaosbane (Simplified Chinese, English, Korean, Traditional Chinese)", "price": "Rp 699,000"},
{"title": "FINAL FANTASY XV ROYAL EDITION (English, Japanese)", "price": "Rp 699,000"},
{"title": "Tom Clancy's The Division - Digital Standard Edition PlayStation®Hits (Simplified Chinese, English, Korean, Traditional Chinese)", "price": "Rp 699,000"},
{"title": "Bee Simulator (Simplified Chinese, English, Korean, Traditional Chinese)", "price": "Rp 699,000"},
{"title": "Werewolf: The Apocalypse – Earthblood (Simplified Chinese, English, Korean, Traditional Chinese)", "price": "Rp 699,000"},
{"title": "Werewolf: The Apocalypse – Earthblood (Simplified Chinese, English, Korean, Traditional Chinese)", "price": "Rp 699,000"},
{"title": "AO Tennis 2 (Simplified Chinese, English, Korean, Traditional Chinese)", "price": "Rp 699,000"},
{"title": "ALIENATION™ (English)", "price": "Rp 699,000"},
{"title": "inFAMOUS First Light™ full game (English/Chinese/Korean Ver.)", "price": "Rp 699,000"},
{"title": "AVICII Invector (Simplified Chinese, English, Korean, Japanese)", "price": "Rp 699,000"},
{"title": "FINAL FANTASY VII REMAKE (English/Japanese Ver.)", "price": "Rp 699,000"},
{"title": "WORLD OF FINAL FANTASY (English Ver.)", "price": "Rp 699,000"},
{"title": "Portal Knights (Simplified Chinese, English, Korean)", "price": "Rp 699,000"},
{"title": "Child Of Light (English/Japanese Ver.)", "price": "Rp 699,000"},
{"title": "Hotshot Racing (Simplified Chinese, English, Korean, Japanese, Traditional Chinese)", "price": "Rp 699,000"},
{"title": "KINGDOM HEARTS Melody of Memory (English)", "price": "Rp 699,000"},
{"title": "The Surge (Simplified Chinese, English, Korean)", "price": "Rp 699,000"},
{"title": "OVERPASS™ (Simplified Chinese, English, Korean, Traditional Chinese)", "price": "Rp 699,000"},
{"title": "Oddworld: Soulstorm Enhanced Edition (Simplified Chinese, English, Japanese, Traditional Chinese)", "price": "Rp 699,000"},
{"title": "Necromunda: Underhive Wars (Simplified Chinese, English)", "price": "Rp 699,000"},
{"title": "Just Cause 4: Reloaded (English Ver.)", "price": "Rp 699,000"},
{"title": "DYNASTY WARRIORS 8 Empires full game (English Ver.)", "price": "Rp 606,000"},
{"title": "DYNASTY WARRIORS 8 Empires full game (Traditional Chinese)", "price": "Rp 606,000"},
{"title": "DEATH STRANDING Standard Digital Edition (Simplified Chinese, English, Korean, Traditional Chinese)", "price": "Rp 606,000"},
{"title": "DEATH STRANDING DIRECTOR’S CUT (Simplified Chinese, English, Korean, Japanese, Traditional Chinese)", "price": "Rp 606,000"},
{"title": "TRIALS of MANA (Simplified Chinese, Korean, Traditional Chinese)", "price": "Rp 606,000"},
{"title": "TRIALS of MANA (English/Japanese Ver.)", "price": "Rp 606,000"}
]